LICENSE
README.md
setup.py
whttpserver/__init__.py
whttpserver/__main__.py
whttpserver.egg-info/PKG-INFO
whttpserver.egg-info/SOURCES.txt
whttpserver.egg-info/dependency_links.txt
whttpserver.egg-info/entry_points.txt
whttpserver.egg-info/requires.txt
whttpserver.egg-info/top_level.txt
whttpserver/templates/edit_file.html
whttpserver/templates/index.html