Metadata-Version: 2.1
Name: whttpserver
Version: 1.6.2
Summary: A simple HTTP server like `python -m http.server`
Home-page: https://www.ddz.cool
Author: Wang Junbo
Author-email: wjbhnu@gmail.com
License: UNKNOWN
Platform: UNKNOWN
Classifier: Programming Language :: Python :: 2
Classifier: Programming Language :: Python :: 3
Classifier: License :: OSI Approved :: MIT License
Classifier: Operating System :: OS Independent
Requires-Python: >=2.7
